README.md
setup.py
dict2object/__init__.py
dict2object/errorException.py
dict2object/jsonObject.py
dictionary_to_object.egg-info/PKG-INFO
dictionary_to_object.egg-info/SOURCES.txt
dictionary_to_object.egg-info/dependency_links.txt
dictionary_to_object.egg-info/top_level.txt