Metadata-Version: 1.1
Name: dictionary-to-object
Version: 0.0.1
Summary: Python dictionray to Object
Home-page: https://github.com/krypton-byte/dict2object
Author: Krypton Byte
Author-email: galaxyvplus6434@gmail.com
License: MIT
Download-URL: https://github.com/krypton-byte/dict2object/archive/0.0.1.tar.gz
Keywords: json,dictionary,object,toObject
Platform: UNKNOWN
Classifier: Development Status :: 3 - Alpha
Classifier: Intended Audience :: Developers
Classifier: Topic :: Software Development :: Build Tools
Classifier: License :: OSI Approved :: MIT License
Classifier: Programming Language :: Python :: 3.8
Classifier: Programming Language :: Python :: 3.9
